README.md
setup.py
gorani/__init__.py
gorani/utils.py
gorani.egg-info/PKG-INFO
gorani.egg-info/SOURCES.txt
gorani.egg-info/dependency_links.txt
gorani.egg-info/requires.txt
gorani.egg-info/top_level.txt
gorani/booky/__init__.py
gorani/booky/book.py
gorani/booky/epub_converter.py