Metadata-Version: 2.1
Name: gorani
Version: 1.0.6
Summary: Gorani Reader data pipeline utility
Home-page: UNKNOWN
Author: Sunho Kim
Author-email: ksunhokim123@naver.com
License: UNKNOWN
Platform: UNKNOWN
Classifier: Programming Language :: Python :: 3
Requires-Python: >=3.6
